pycloudxns/__init__.py
pycloudxns/cloudxns.py
pycloudxns/request.py
pycloudxns/xns.py
pycloudxns/xnsrecord.py
pycloudxns-0.0.11.dist-info/METADATA
pycloudxns-0.0.11.dist-info/WHEEL
pycloudxns-0.0.11.dist-info/top_level.txt
pycloudxns-0.0.11.dist-info/RECORD
